{
  "name": "aux_classificadores",
  "profile": "tabular-data-package",
  "resources": [
    {
      "name": "acao",
      "type": "table",
      "profile": "tabular-data-resource",
      "path": "data/acao.csv",
      "scheme": "file",
      "format": "csv",
      "mediatype": "text/csv",
      "encoding": "utf-8",
      "hash": "sha256:c7c86bd7686f0d4f17aab76907fb551ff14bf7f2a63caf468d882ef05644bcf0",
      "bytes": 1032363,
      "fields": 4,
      "rows": 14070,
      "dialect": {
        "csv": {
          "delimiter": ","
        }
      },
      "schema": {
        "fields": [
          {
            "name": "chave_acao",
            "type": "string"
          },
          {
            "name": "ano",
            "type": "integer"
          },
          {
            "name": "acao_cod",
            "type": "integer"
          },
          {
            "name": "acao_desc",
            "type": "string"
          }
        ],
        "primaryKey": [
          "ano",
          "acao_cod"
        ]
      }
    },
    {
      "name": "elemento_item",
      "type": "table",
      "profile": "tabular-data-resource",
      "path": "data/elemento_item.csv",
      "scheme": "file",
      "format": "csv",
      "mediatype": "text/csv",
      "encoding": "utf-8",
      "hash": "sha256:f3182ed8e3ae98280dd74024afb1b0954dc07cf11989a360d018543124546a52",
      "bytes": 407097,
      "fields": 4,
      "rows": 6987,
      "dialect": {
        "csv": {
          "delimiter": ","
        }
      },
      "schema": {
        "fields": [
          {
            "name": "chave_elemento_item",
            "type": "string"
          },
          {
            "name": "ano",
            "type": "integer"
          },
          {
            "name": "elemento_item_cod",
            "type": "integer"
          },
          {
            "name": "elemento_item_desc",
            "type": "string"
          }
        ],
        "primaryKey": [
          "ano",
          "elemento_item_cod"
        ]
      }
    },
    {
      "name": "fonte_recurso",
      "type": "table",
      "profile": "tabular-data-resource",
      "path": "data/fonte_recurso.csv",
      "scheme": "file",
      "format": "csv",
      "mediatype": "text/csv",
      "encoding": "utf-8",
      "hash": "sha256:cdf30a122d8a5de57f716a96bd50bcb9755df50accf54048df33f1e5f601d854",
      "bytes": 55079,
      "fields": 4,
      "rows": 805,
      "dialect": {
        "csv": {
          "delimiter": ","
        }
      },
      "schema": {
        "fields": [
          {
            "name": "chave_fonte_recurso",
            "type": "string"
          },
          {
            "name": "ano",
            "type": "integer"
          },
          {
            "name": "fonte_cod",
            "type": "integer"
          },
          {
            "name": "fonte_desc",
            "type": "string"
          }
        ],
        "primaryKey": [
          "ano",
          "fonte_cod"
        ]
      }
    },
    {
      "name": "funcional_programatica",
      "type": "table",
      "profile": "tabular-data-resource",
      "path": "data/funcional_programatica.csv",
      "scheme": "file",
      "format": "csv",
      "mediatype": "text/csv",
      "encoding": "utf-8",
      "hash": "sha256:395bdb2dba6adecbfa940d75d70ce0f6b01b5e9352e7b500cec9cfd0e56ae935",
      "bytes": 4198350,
      "fields": 11,
      "rows": 18071,
      "dialect": {
        "csv": {
          "delimiter": ","
        }
      },
      "schema": {
        "fields": [
          {
            "name": "chave_funcional_programatica",
            "type": "string"
          },
          {
            "name": "ano",
            "type": "integer"
          },
          {
            "name": "uo_cod",
            "type": "integer"
          },
          {
            "name": "funcao_cod",
            "type": "integer"
          },
          {
            "name": "funcao_desc",
            "type": "string"
          },
          {
            "name": "subfuncao_cod",
            "type": "integer"
          },
          {
            "name": "subfuncao_desc",
            "type": "string"
          },
          {
            "name": "programa_cod",
            "type": "integer"
          },
          {
            "name": "programa_desc",
            "type": "string"
          },
          {
            "name": "acao_cod",
            "type": "integer"
          },
          {
            "name": "acao_desc",
            "type": "string"
          }
        ],
        "primaryKey": [
          "ano",
          "uo_cod",
          "acao_cod"
        ]
      }
    },
    {
      "name": "natureza_receita",
      "type": "table",
      "profile": "tabular-data-resource",
      "path": "data/natureza_receita.csv",
      "scheme": "file",
      "format": "csv",
      "mediatype": "text/csv",
      "encoding": "utf-8",
      "hash": "sha256:c10331d26e396616f0d07be487295d30c82106cf227dada140d5a77f70e0e34f",
      "bytes": 953004,
      "fields": 4,
      "rows": 8776,
      "dialect": {
        "csv": {
          "delimiter": ","
        }
      },
      "schema": {
        "fields": [
          {
            "name": "chave_natureza_receita",
            "type": "string"
          },
          {
            "name": "ano",
            "type": "integer"
          },
          {
            "name": "rec_cod",
            "type": "integer"
          },
          {
            "name": "rec_desc",
            "type": "string"
          }
        ],
        "primaryKey": [
          "ano",
          "rec_cod"
        ]
      }
    },
    {
      "name": "uo",
      "type": "table",
      "profile": "tabular-data-resource",
      "path": "data/uo.csv",
      "scheme": "file",
      "format": "csv",
      "mediatype": "text/csv",
      "encoding": "utf-8",
      "hash": "sha256:aca304a70ca934227176c60fd8001959aede936093eb77cd1c894c3a9e8600b5",
      "bytes": 255388,
      "fields": 10,
      "rows": 1709,
      "dialect": {
        "csv": {
          "delimiter": ","
        }
      },
      "schema": {
        "fields": [
          {
            "name": "chave_uo",
            "type": "string"
          },
          {
            "name": "ano",
            "type": "integer"
          },
          {
            "name": "orgao_vinculacao_cod",
            "type": "integer"
          },
          {
            "name": "orgao_vinculacao_nome",
            "type": "string"
          },
          {
            "name": "poder_cod",
            "type": "integer"
          },
          {
            "name": "poder_desc",
            "type": "string"
          },
          {
            "name": "uo_cod",
            "type": "integer"
          },
          {
            "name": "uo_nome",
            "type": "string"
          },
          {
            "name": "uo_sigla",
            "type": "string"
          },
          {
            "name": "uo_sigla_current",
            "type": "string"
          }
        ],
        "primaryKey": [
          "ano",
          "uo_cod"
        ]
      }
    }
  ],
  "updated_at": "2025-10-10T09:39:37"
}